XinGainianMoniDianlu3YunsuanFangdaqiDePinlvtexingHeLvboqi/README.md
XinGainianMoniDianlu3YunsuanFangdaqiDePinlvtexingHeLvboqi/__init__.py
XinGainianMoniDianlu3YunsuanFangdaqiDePinlvtexingHeLvboqi/__main__.py
XinGainianMoniDianlu3YunsuanFangdaqiDePinlvtexingHeLvboqi/file.pdf
XinGainianMoniDianlu3YunsuanFangdaqiDePinlvtexingHeLvboqi/index.html
xin_gainian_moni_dianlu_3_yunsuan_fangdaqi_de_pinlvtexing_he_lvboqi-2024.3.5.0.dist-info/METADATA
xin_gainian_moni_dianlu_3_yunsuan_fangdaqi_de_pinlvtexing_he_lvboqi-2024.3.5.0.dist-info/WHEEL
xin_gainian_moni_dianlu_3_yunsuan_fangdaqi_de_pinlvtexing_he_lvboqi-2024.3.5.0.dist-info/entry_points.txt
xin_gainian_moni_dianlu_3_yunsuan_fangdaqi_de_pinlvtexing_he_lvboqi-2024.3.5.0.dist-info/top_level.txt
xin_gainian_moni_dianlu_3_yunsuan_fangdaqi_de_pinlvtexing_he_lvboqi-2024.3.5.0.dist-info/RECORD
