Metadata-Version: 2.1
Name: xin-gainian-moni-dianlu-3-yunsuan-fangdaqi-de-pinlvtexing-he-lvboqi
Version: 2024.3.5.0
Summary: 新概念模拟电路3-运算放大器的频率特性和滤波器
Home-page: https://github.com/apachecn/xin-gainian-moni-dianlu-3-yunsuan-fangdaqi-de-pinlvtexing-he-lvboqi
Author: ApacheCN
Author-email: apachecn@163.com
License: UNKNOWN
Platform: UNKNOWN
Classifier: Development Status :: 4 - Beta
Classifier: Environment :: Console
Classifier: Intended Audience :: Developers
Classifier: Intended Audience :: End Users/Desktop
Classifier: License :: Other/Proprietary License
Classifier: Natural Language :: Chinese (Simplified)
Classifier: Natural Language :: English
Classifier: Operating System :: OS Independent
Classifier: Programming Language :: Python :: 3
Classifier: Programming Language :: Python :: 3 :: Only
Classifier: Programming Language :: Python :: 3.6
Classifier: Programming Language :: Python :: 3.7
Classifier: Topic :: Text Processing :: Markup :: Markdown
Classifier: Topic :: Text Processing :: Markup :: HTML
Classifier: Topic :: Internet :: WWW/HTTP
Classifier: Topic :: Software Development :: Documentation
Classifier: Topic :: Documentation
Requires-Python: >=3.6
